vscode_task_runner/__init__.py
vscode_task_runner/__main__.py
vscode_task_runner/console.py
vscode_task_runner/constants.py
vscode_task_runner/exceptions.py
vscode_task_runner/executor.py
vscode_task_runner/models/arg_parser.py
vscode_task_runner/models/enums.py
vscode_task_runner/models/input.py
vscode_task_runner/models/options.py
vscode_task_runner/models/properties.py
vscode_task_runner/models/shell.py
vscode_task_runner/models/strings.py
vscode_task_runner/models/task.py
vscode_task_runner/models/tasks.py
vscode_task_runner/parser.py
vscode_task_runner/printer.py
vscode_task_runner/utils/paths.py
vscode_task_runner/utils/picker.py
vscode_task_runner/utils/shell.py
vscode_task_runner/utils/strings.py
vscode_task_runner/variables/resolve.py
vscode_task_runner/variables/runtime.py
vscode_task_runner/variables/static.py
vscode_task_runner/vscode/task_configuration.py
vscode_task_runner/vscode/terminal_task_system.py
vscode_task_runner-3.0.1.dist-info/WHEEL
vscode_task_runner-3.0.1.dist-info/entry_points.txt
vscode_task_runner-3.0.1.dist-info/METADATA
vscode_task_runner-3.0.1.dist-info/RECORD
