Metadata-Version: 2.3
Name: vscode-task-runner
Version: 3.0.1
Summary: Task runner for VS Code tasks.json
Author: Nathan Vaughn
Author-email: Nathan Vaughn <nath@nvaughn.email>
Classifier: Intended Audience :: Developers
Classifier: Topic :: Software Development :: Libraries :: Python Modules
Classifier: Topic :: Software Development :: Build Tools
Classifier: License :: OSI Approved :: MIT License
Classifier: Programming Language :: Python :: 3.9
Classifier: Programming Language :: Python :: 3.10
Classifier: Programming Language :: Python :: 3.11
Classifier: Programming Language :: Python :: 3.12
Classifier: Programming Language :: Python :: 3.13
Classifier: Programming Language :: Python :: 3.14
Requires-Dist: shellingham>=1.5.4
Requires-Dist: pyjson5>=1.6.7
Requires-Dist: questionary>=2.0.1
Requires-Dist: colorama>=0.4.6
Requires-Dist: pydantic>=2.11.3
Requires-Python: >=3.9
Project-URL: Homepage, https://github.com/NathanVaughn/vscode-task-runner
Project-URL: Issues, https://github.com/NathanVaughn/vscode-task-runner/issues
Project-URL: Repository, https://github.com/NathanVaughn/vscode-task-runner.git
